alphatools/__init__.py
alphatools/backtesting_app.py
alphatools/utils/__init__.py
alphatools/utils/alphatools_prompt.py
alphatools/utils/cache.py
alphatools/utils/instrument_pnl_calculator.py
alphatools/utils/instruments.py
alphatools/utils/pnl_calculator.py
alphatools/utils/smartapi_helper.py
alphatools/utils/token_manager.py
alphatools_jv-3.4.1.data/scripts/instruments_cli.py
alphatools_jv-3.4.1.data/scripts/price_archiver.py
alphatools_jv-3.4.1.data/scripts/smartapi_query.py
test/__init__.py
test/test_backtesting_app.py
test/test_pnl_calculator.py
alphatools_jv-3.4.1.dist-info/METADATA
alphatools_jv-3.4.1.dist-info/WHEEL
alphatools_jv-3.4.1.dist-info/top_level.txt
alphatools_jv-3.4.1.dist-info/RECORD
