Metadata-Version: 2.1
Name: alphatools-jv
Version: 3.4.1
Summary: Wrapper over angel broking smartapi to read cached options market data
Home-page: https://github.com/jaskirat1208/backtest-platform
Author: Jaskirat Singh
Author-email: jaskiratsingh1208@gmail.com
Classifier: Programming Language :: Python :: 3
Classifier: License :: OSI Approved :: MIT License
Requires-Dist: twine
Requires-Dist: wheel
Requires-Dist: smartapi-python
Requires-Dist: websocket-client
Requires-Dist: multipledispatch (~=0.6.0)
Requires-Dist: mintotp (~=0.3.0)
Requires-Dist: requests (~=2.28.1)
Requires-Dist: pandas (~=1.5.2)
Requires-Dist: setuptools (~=65.5.1)
Requires-Dist: python-semantic-release (==7.2.0)
